commoncorrections/__init__.py
commoncorrections/commoncorrections.py
commoncorrections/corrections.csv
commoncorrections-1.0.12.dist-info/LICENSE
commoncorrections-1.0.12.dist-info/METADATA
commoncorrections-1.0.12.dist-info/WHEEL
commoncorrections-1.0.12.dist-info/top_level.txt
commoncorrections-1.0.12.dist-info/RECORD
