Metadata-Version: 2.1
Name: commoncorrections
Version: 1.0.12
Summary: A small python implementation of common ASR corrections
Home-page: https://github.com/robmsmt/CommonCorrections
Author: Rob Smith
Author-email: robmsmt@gmail.com
Classifier: Programming Language :: Python :: 3
Classifier: License :: OSI Approved :: Apache Software License
Classifier: Operating System :: OS Independent
Requires-Python: >=3.6
License-File: LICENSE
Requires-Dist: pandas
Requires-Dist: inflect
Requires-Dist: requests
